MANIFEST.in
README.rst
setup.py
dbnet/__init__.py
dbnet/cli.py
dbnet/server.py
dbnet/store.py
dbnet/worker_db.py
dbnet/worker_mon.py
dbnet/worker_web.py
dbnet.egg-info/PKG-INFO
dbnet.egg-info/SOURCES.txt
dbnet.egg-info/dependency_links.txt
dbnet.egg-info/entry_points.txt
dbnet.egg-info/requires.txt
dbnet.egg-info/top_level.txt
dbnet/static/favicon.ico
dbnet/static/css/app.aba29537.css
dbnet/static/css/chunk-vendors.4e10713f.css
dbnet/static/fonts/fontawesome-webfont.674f50d2.eot
dbnet/static/fonts/fontawesome-webfont.af7ae505.woff2
dbnet/static/fonts/fontawesome-webfont.b06871f2.ttf
dbnet/static/fonts/fontawesome-webfont.fee66e71.woff
dbnet/static/img/fontawesome-webfont.912ec66d.svg
dbnet/static/img/logo-brand.a3616106.png
dbnet/static/js/app.4d56d4e9.js
dbnet/static/js/app.4d56d4e9.js.map
dbnet/static/js/chunk-vendors.6852a4cd.js
dbnet/static/js/chunk-vendors.6852a4cd.js.map
dbnet/templates/index.html
dbnet/templates/login.html